weldnumpy-0.2.0.data/purelib/weldnumpy/README.md
weldnumpy-0.2.0.data/purelib/weldnumpy/__init__.py
weldnumpy-0.2.0.data/purelib/weldnumpy/weldarray.py
weldnumpy-0.2.0.data/purelib/weldnumpy/weldnumpy.py
weldnumpy-0.2.0.data/purelib/weldnumpy/weldrandom.py
weldnumpy-0.2.0.data/purelib/weldnumpy/examples/blackscholes.py
weldnumpy-0.2.0.data/purelib/weldnumpy/tests/__init__.py
weldnumpy-0.2.0.data/purelib/weldnumpy/tests/test_1d.py
weldnumpy-0.2.0.data/purelib/weldnumpy/tests/test_common.py
weldnumpy-0.2.0.data/purelib/weldnumpy/tests/test_multid.py
weldnumpy-0.2.0.data/purelib/weldnumpy/tests/test_utils.py
weldnumpy-0.2.0.dist-info/DESCRIPTION.rst
weldnumpy-0.2.0.dist-info/METADATA
weldnumpy-0.2.0.dist-info/RECORD
weldnumpy-0.2.0.dist-info/WHEEL
weldnumpy-0.2.0.dist-info/metadata.json
weldnumpy-0.2.0.dist-info/top_level.txt
