Metadata-Version: 2.0
Name: weldnumpy
Version: 0.2.0
Summary: UNKNOWN
Home-page: https://github.com/parimarjan/weld/tree/master/python/numpy
Author: Weld Developers
Author-email: weld-group@lists.stanford.edu
License: UNKNOWN
Platform: UNKNOWN
Requires-Dist: numpy (>=1.13)
Requires-Dist: pytest
Requires-Dist: pyweld
Requires-Dist: scipy
